{
  "_class": "symbolInstance",
  "booleanOperation": 0,
  "do_objectID": "8E3B264A-99DE-43D3-844A-F7659E624FE2",
  "exportOptions": {
    "_class": "exportOptions",
    "do_objectID": "2B6EACC1-9079-4C79-B4CB-0E4783C5A12B",
    "exportFormats": [
    ],
    "includedLayerIds": [
    ],
    "layerOptions": 0,
    "shouldTrim": false
  },
  "frame": {
    "_class": "rect",
    "constrainProportions": false,
    "do_objectID": "35FF2F22-BA87-4F41-BE6F-2F4EB73D3FE3",
    "height": 24,
    "width": 24,
    "x": 0,
    "y": 0
  },
  "horizontalSpacing": 0,
  "isFixedToViewport": false,
  "isFlippedHorizontal": false,
  "isFlippedVertical": false,
  "isLocked": false,
  "isVisible": true,
  "layerListExpandedType": 0,
  "name": "Icons/Communication/ic_call",
  "nameIsFixed": false,
  "overrideValues": [
  ],
  "resizingConstraint": 63,
  "resizingType": 0,
  "rotation": 0,
  "scale": 1,
  "shouldBreakMaskChain": false,
  "style": {
    "_class": "style",
    "contextSettings": {
      "_class": "graphicsContextSettings",
      "blendMode": 0,
      "do_objectID": "CE767E53-38CB-4FD3-827F-E2872A70C8FE",
      "opacity": 0.5
    },
    "do_objectID": "BBA2059A-81B9-4AFA-848D-12789E11DF00",
    "endMarkerType": 0,
    "miterLimit": 10,
    "startMarkerType": 0,
    "windingRule": 1
  },
  "symbolID": "34EC78DB-4344-4B79-B485-2C6AF57635D6",
  "verticalSpacing": 0
}