{
  "_class": "shapeGroup",
  "booleanOperation": 0,
  "clippingMaskMode": 0,
  "do_objectID": "58FE02C4-CB8F-44BC-95E4-38D58DCB1CBE",
  "exportOptions": {
    "_class": "exportOptions",
    "do_objectID": "45421D26-3EE1-4118-BF53-7786D4F3F225",
    "exportFormats": [
    ],
    "includedLayerIds": [
    ],
    "layerOptions": 0,
    "shouldTrim": false
  },
  "frame": {
    "_class": "rect",
    "constrainProportions": false,
    "do_objectID": "C352869F-DF2E-422B-B1BF-1DCE050A8683",
    "height": 35.93714583333333,
    "width": 59.51020408163265,
    "x": 0.2448979591836746,
    "y": 0.07497916666666526
  },
  "hasClickThrough": false,
  "hasClippingMask": false,
  "isFixedToViewport": false,
  "isFlippedHorizontal": false,
  "isFlippedVertical": false,
  "isLocked": false,
  "isVisible": true,
  "layerListExpandedType": 0,
  "layers": [
    {
      "class": "shapePath",
      "id": "15D95E5F-17DB-47F5-ABE3-B89302B90F96"
    }
  ],
  "name": "Fill 6",
  "nameIsFixed": false,
  "resizingConstraint": 63,
  "resizingType": 0,
  "rotation": 0,
  "shouldBreakMaskChain": false,
  "style": {
    "_class": "style",
    "do_objectID": "A45FB1C4-43ED-4E1B-B576-A8BE190C87F6",
    "endMarkerType": 0,
    "fills": [
      {
        "_class": "fill",
        "color": {
          "_class": "color",
          "alpha": 1,
          "blue": 0.306,
          "green": 0.808,
          "red": 0.643
        },
        "fillType": 0,
        "isEnabled": true,
        "noiseIndex": 0,
        "noiseIntensity": 0,
        "patternFillType": 1,
        "patternTileScale": 1
      }
    ],
    "miterLimit": 10,
    "startMarkerType": 0,
    "windingRule": 1
  },
  "windingRule": 1
}