{
  "_class": "text",
  "attributedString": {
    "_class": "attributedString",
    "attributes": [
      {
        "_class": "stringAttribute",
        "attributes": {
          "MSAttributedStringColorAttribute": {
            "_class": "color",
            "alpha": 1,
            "blue": 0.6274509803921569,
            "green": 0.3803921568627452,
            "red": 0
          },
          "MSAttributedStringFontAttribute": {
            "_class": "fontDescriptor",
            "attributes": {
              "name": "Roboto-Bold",
              "size": 20
            }
          },
          "paragraphStyle": {
            "_class": "paragraphStyle",
            "allowsDefaultTighteningForTruncation": 0,
            "maximumLineHeight": 16,
            "minimumLineHeight": 16,
            "paragraphSpacing": 10
          }
        },
        "length": 19,
        "location": 0
      }
    ],
    "string": "Owner’s Information"
  },
  "automaticallyDrawOnUnderlyingPath": false,
  "booleanOperation": 0,
  "do_objectID": "BE1CE320-E4E5-49F4-B7A1-F5BED0FE7691",
  "dontSynchroniseWithSymbol": false,
  "exportOptions": {
    "_class": "exportOptions",
    "do_objectID": "930869F2-804E-4EF9-A61D-C7CA29115519",
    "exportFormats": [
    ],
    "includedLayerIds": [
    ],
    "layerOptions": 0,
    "shouldTrim": false
  },
  "frame": {
    "_class": "rect",
    "constrainProportions": false,
    "do_objectID": "7513C8B4-5712-4EB1-A742-3545B72378E0",
    "height": 16,
    "width": 181,
    "x": 15,
    "y": 159
  },
  "glyphBounds": "{{0, -1}, {180, 17}}",
  "isFixedToViewport": false,
  "isFlippedHorizontal": false,
  "isFlippedVertical": false,
  "isLocked": false,
  "isVisible": true,
  "layerListExpandedType": 0,
  "lineSpacingBehaviour": 2,
  "name": "Owner’s Information",
  "nameIsFixed": false,
  "resizingConstraint": 47,
  "resizingType": 0,
  "rotation": 0,
  "shouldBreakMaskChain": false,
  "style": {
    "_class": "style",
    "do_objectID": "A80D4DC6-63DF-44AE-8E17-F94C655D54AE",
    "endMarkerType": 0,
    "miterLimit": 10,
    "sharedObjectID": "9367F679-155A-4D8A-9FC8-6BD1284485B8",
    "startMarkerType": 0,
    "textStyle": {
      "_class": "textStyle",
      "do_objectID": "21F0FA20-6418-445B-8A31-2135350EC6FA",
      "encodedAttributes": {
        "MSAttributedStringColorAttribute": {
          "_class": "color",
          "alpha": 1,
          "blue": 0.6274509803921569,
          "green": 0.3803921568627452,
          "red": 0
        },
        "MSAttributedStringFontAttribute": {
          "_class": "fontDescriptor",
          "attributes": {
            "name": "Roboto-Bold",
            "size": 20
          }
        },
        "paragraphStyle": {
          "_class": "paragraphStyle",
          "allowsDefaultTighteningForTruncation": 0,
          "maximumLineHeight": 16,
          "minimumLineHeight": 16,
          "paragraphSpacing": 10
        }
      },
      "verticalAlignment": 0
    },
    "windingRule": 1
  },
  "textBehaviour": 0
}